{"meta":{"code":200,"requestId":"5a56b35c9fb6b75d49f0da92"},"response":{"suggestedFilters":{"header":"Toque para exibir:","filters":[{"name":"Abertos agora","key":"openNow"}]},"suggestedRadius":600,"headerLocation":"Bela Vista","headerFullLocation":"Bela Vista, São Paulo","headerLocationGranularity":"neighborhood","totalResults":131,"suggestedBounds":{"ne":{"lat":-23.565595428121412,"lng":-46.644446203277745},"sw":{"lat":-23.568650265766024,"lng":-46.649035746309885}},"groups":[{"type":"Recommended Places","name":"recommended","items":[{"reasons":{"count":0,"items":[{"summary":"Este lugar é popular","type":"general","reasonName":"globalInteractionReason"}]},"venue":{"id":"4d458492e198721eafa9c68b","name":"Osteria Generale","contact":{"phone":"+551132535572","formattedPhone":"+55 11 3253-5572","twitter":"cantinagenerale","facebook":"700095613368505","facebookUsername":"osteriagenerale","facebookName":"Osteria Generale"},"location":{"address":"R. Dr. Fausto Ferraz, 163","lat":-23.565734284377985,"lng":-46.64679178268468,"labeledLatLngs":[{"label":"display","lat":-23.565734284377985,"lng":-46.64679178268468}],"distance":105,"postalCode":"01333-030","cc":"BR","city":"São Paulo","state":"SP","country":"Brasil","formattedAddress":["R. Dr. Fausto Ferraz, 163","São Paulo, SP","01333-030","Brasil"]},"categories":[{"id":"4bf58dd8d48988d110941735","name":"Restaurante Italiano","pluralName":"Restaurantes Italianos","shortName":"Italiano","icon":{"prefix":"https:\/\/ss3.4sqi.net\/img\/categories_v2\/food\/italian_","suffix":".png"},"primary":true}],"verified":false,"stats":{"checkinsCount":10566,"usersCount":5026,"tipCount":294},"url":"http:\/\/www.generale.com.br","price":{"tier":3,"message":"Caro","currency":"$"},"rating":9.1,"ratingColor":"00B551","ratingSignals":1240,"allowMenuUrlEdit":true,"beenHere":{"count":0,"marked":false,"lastCheckinExpiredAt":0},"hours":{"status":"Aberto até Meia-noite","richStatus":{"entities":[],"text":"Aberto até Meia-noite"},"isOpen":true,"isLocalHoliday":false},"photos":{"count":1,"groups":[{"type":"venue","name":"Fotos do lugar","count":1,"items":[{"id":"518188dc498e1b40c4628675","createdAt":1367443676,"prefix":"https:\/\/igx.4sqi.net\/img\/general\/","suffix":"\/4029224_YEjnsyK-VgLX1boaogWCnG4vOM0ESq9HpXRIccz0fQ4.jpg","width":1918,"height":1434,"user":{"id":"4029224","firstName":"Ana","lastName":"Santana","gender":"female","photo":{"prefix":"https:\/\/igx.4sqi.net\/img\/user\/","suffix":"\/OCJUAI433NFIWHNT.jpg"}},"visibility":"public"}]}]},"hereNow":{"count":0,"summary":"Não há ninguém aqui","groups":[]},"featuredPhotos":{"count":1,"items":[{"id":"518188dc498e1b40c4628675","createdAt":1367443676,"prefix":"https:\/\/igx.4sqi.net\/img\/general\/","suffix":"\/4029224_YEjnsyK-VgLX1boaogWCnG4vOM0ESq9HpXRIccz0fQ4.jpg","width":1918,"height":1434,"user":{"id":"4029224","firstName":"Ana","lastName":"Santana","gender":"female","photo":{"prefix":"https:\/\/igx.4sqi.net\/img\/user\/","suffix":"\/OCJUAI433NFIWHNT.jpg"}},"visibility":"public"}]}},"tips":[{"id":"4d802069551ea1cd923315c5","createdAt":1300242537,"text":"Não deixe de experimentar a torrada com alho deles! Muito boa!","type":"user","canonicalUrl":"https:\/\/foursquare.com\/item\/4d802069551ea1cd923315c5","likes":{"count":24,"groups":[],"summary":"24 curtir"},"logView":true,"agreeCount":23,"disagreeCount":0,"todo":{"count":0},"user":{"id":"4639218","firstName":"Gui","lastName":"Neves","gender":"male","photo":{"prefix":"https:\/\/igx.4sqi.net\/img\/user\/","suffix":"\/4639218_TOa4oSsl_dTYQLcgMMvWcpBU4_hTsqHPgc_dDAGeu57-GJ8Q2_r5RuyOFYPLvS8vlU4KxVaDr.jpg"}}}],"referralId":"e-0-4d458492e198721eafa9c68b-0"},{"reasons":{"count":0,"items":[{"summary":"Este lugar é popular","type":"general","reasonName":"globalInteractionReason"}]},"venue":{"id":"4b363138f964a520ee3025e3","name":"Competition","contact":{"phone":"+551131499777","formattedPhone":"+55 11 3149-9777","twitter":"competitionsp","instagram":"competitionacademia","facebook":"197296513618803","facebookUsername":"Competitionacademia","facebookName":"Competition Academia"},"location":{"address":"R. Cincinato Braga, 520","lat":-23.56704353731889,"lng":-46.64755456815419,"labeledLatLngs":[{"label":"display","lat":-23.56704353731889,"lng":-46.64755456815419}],"distance":127,"postalCode":"01333-010","cc":"BR","city":"São Paulo","state":"SP","country":"Brasil","formattedAddress":["R. Cincinato Braga, 520","São Paulo, SP","01333-010","Brasil"]},"categories":[{"id":"4bf58dd8d48988d175941735","name":"Academia de Ginástica","pluralName":"Academias de Ginástica","shortName":"Academia \/ Ginástica","icon":{"prefix":"https:\/\/ss3.4sqi.net\/img\/categories_v2\/building\/gym_","suffix":".png"},"primary":true}],"verified":false,"stats":{"checkinsCount":21733,"usersCount":1567,"tipCount":60},"url":"http:\/\/www.competition.com.br","rating":8.8,"ratingColor":"73CF42","ratingSignals":382,"venueRatingBlacklisted":true,"allowMenuUrlEdit":true,"beenHere":{"count":0,"marked":false,"lastCheckinExpiredAt":0},"hours":{"status":"Aberto até 23:00","richStatus":{"entities":[],"text":"Aberto até 23:00"},"isOpen":true,"isLocalHoliday":false},"photos":{"count":1,"groups":[{"type":"venue","name":"Fotos do lugar","count":1,"items":[{"id":"50298b60e4b0f474030a6153","createdAt":1344899936,"prefix":"https:\/\/igx.4sqi.net\/img\/general\/","suffix":"\/nRnCMknT4XLq0CvtBfQHlPi72laFFRoqEEU9C9W-JiA.jpg","width":720,"height":537,"user":{"id":"7454133","firstName":"Joao","lastName":"Federici","gender":"male","photo":{"prefix":"https:\/\/igx.4sqi.net\/img\/user\/","suffix":"\/FLYYLPF1NMJJKMJA.jpg"}},"visibility":"public"}]}]},"hereNow":{"count":1,"summary":"Uma outra pessoa está aqui","groups":[{"type":"others","name":"Outras pessoas aqui","count":1,"items":[]}]},"featuredPhotos":{"count":1,"items":[{"id":"50298b60e4b0f474030a6153","createdAt":1344899936,"prefix":"https:\/\/igx.4sqi.net\/img\/general\/","suffix":"\/nRnCMknT4XLq0CvtBfQHlPi72laFFRoqEEU9C9W-JiA.jpg","width":720,"height":537,"user":{"id":"7454133","firstName":"Joao","lastName":"Federici","gender":"male","photo":{"prefix":"https:\/\/igx.4sqi.net\/img\/user\/","suffix":"\/FLYYLPF1NMJJKMJA.jpg"}},"visibility":"public"}]}},"tips":[{"id":"515e0398e4b0ba34f8addac6","createdAt":1365115800,"text":"Variedade de aulas, equipe de professores atenciosos, equipamentos modernos e ambiente agradável! Vale o investimento.","type":"user","canonicalUrl":"https:\/\/foursquare.com\/item\/515e0398e4b0ba34f8addac6","likes":{"count":14,"groups":[],"summary":"14 curtir"},"logView":true,"agreeCount":14,"disagreeCount":0,"todo":{"count":0},"user":{"id":"11143899","firstName":"Vanessa","lastName":"Fortunato","gender":"female","photo":{"prefix":"https:\/\/igx.4sqi.net\/img\/user\/","suffix":"\/D5T0ZNPXG4KU5UBL.jpg"}}}],"referralId":"e-0-4b363138f964a520ee3025e3-1"},{"reasons":{"count":0,"items":[{"summary":"Este lugar é popular","type":"general","reasonName":"globalInteractionReason"}]},"venue":{"id":"4dcd9439d4c065592f6937e8","name":"Raful Cozinha Árabe","contact":{"phone":"+551131712955","formattedPhone":"+55 11 3171-2955"},"location":{"address":"Av. Brg. Luís Antônio, 2159","lat":-23.566777382412337,"lng":-46.648496459827705,"labeledLatLngs":[{"label":"display","lat":-23.566777382412337,"lng":-46.648496459827705}],"distance":214,"postalCode":"01317-002","cc":"BR","city":"São Paulo","state":"SP","country":"Brasil","formattedAddress":["Av. Brg. Luís Antônio, 2159","São Paulo, SP","01317-002","Brasil"]},"categories":[{"id":"4bf58dd8d48988d115941735","name":"Restaurante Árabe","pluralName":"Restaurantes Árabes","shortName":"Árabe","icon":{"prefix":"https:\/\/ss3.4sqi.net\/img\/categories_v2\/food\/middleeastern_","suffix":".png"},"primary":true}],"verified":false,"stats":{"checkinsCount":8192,"usersCount":3780,"tipCount":239},"url":"http:\/\/www.raful.com.br","price":{"tier":2,"message":"Razoável","currency":"$"},"rating":8.8,"ratingColor":"73CF42","ratingSignals":900,"allowMenuUrlEdit":true,"beenHere":{"count":0,"marked":false,"lastCheckinExpiredAt":0},"hours":{"status":"Fechado até 7:00 amanhã","richStatus":{"entities":[],"text":"Fechado até 7:00 amanhã"},"isOpen":false,"isLocalHoliday":false},"photos":{"count":1,"groups":[{"type":"venue","name":"Fotos do lugar","count":1,"items":[{"id":"5192e900498e52f7ba2613ae","createdAt":1368582400,"prefix":"https:\/\/igx.4sqi.net\/img\/general\/","suffix":"\/5938685_z21UkgcFdSncqC-uFgsUONWth1YNrx4YSknkxsKTGBY.jpg","width":612,"height":612,"user":{"id":"5938685","firstName":"Felipe","lastName":"Imperio","gender":"male","photo":{"prefix":"https:\/\/igx.4sqi.net\/img\/user\/","suffix":"\/W5XHLDBMHBPKKTLK.jpg"}},"visibility":"public"}]}]},"hereNow":{"count":0,"summary":"Não há ninguém aqui","groups":[]},"featuredPhotos":{"count":1,"items":[{"id":"5192e900498e52f7ba2613ae","createdAt":1368582400,"prefix":"https:\/\/igx.4sqi.net\/img\/general\/","suffix":"\/5938685_z21UkgcFdSncqC-uFgsUONWth1YNrx4YSknkxsKTGBY.jpg","width":612,"height":612,"user":{"id":"5938685","firstName":"Felipe","lastName":"Imperio","gender":"male","photo":{"prefix":"https:\/\/igx.4sqi.net\/img\/user\/","suffix":"\/W5XHLDBMHBPKKTLK.jpg"}},"visibility":"public"}]}},"tips":[{"id":"4ea5bbe79adff6343b09ae99","createdAt":1319484391,"text":"Esfiha fechada de carne: Simplesmente a melhor que já comi! O preço é tão bom quanto a esfiha! Recomendadíssimo!","type":"user","canonicalUrl":"https:\/\/foursquare.com\/item\/4ea5bbe79adff6343b09ae99","likes":{"count":12,"groups":[],"summary":"12 curtir"},"logView":true,"agreeCount":12,"disagreeCount":0,"todo":{"count":2},"user":{"id":"3597976","firstName":"Helder","gender":"male","photo":{"prefix":"https:\/\/igx.4sqi.net\/img\/user\/","suffix":"\/3597976-CJ2XPNRLXVAOJLTY.jpg"}}}],"referralId":"e-0-4dcd9439d4c065592f6937e8-2"},{"reasons":{"count":0,"items":[{"summary":"Este lugar é popular","type":"general","reasonName":"globalInteractionReason"}]},"venue":{"id":"4daf9e75432d64ea9437fe50","name":"Home Paulista","contact":{"phone":"+551131321600","formattedPhone":"+55 11 3132-1600"},"location":{"address":"R. Carlos Sampaio, 201","crossStreet":"R. Cincinato Braga","lat":-23.567452498950015,"lng":-46.64599584516655,"labeledLatLngs":[{"label":"display","lat":-23.567452498950015,"lng":-46.64599584516655}],"distance":101,"postalCode":"01333-021","cc":"BR","city":"São Paulo","state":"SP","country":"Brasil","formattedAddress":["R. Carlos Sampaio, 201 (R. Cincinato Braga)","São Paulo, SP","01333-021","Brasil"]},"categories":[{"id":"4bf58dd8d48988d1fa931735","name":"Hotel","pluralName":"Hotéis","shortName":"Hotel","icon":{"prefix":"https:\/\/ss3.4sqi.net\/img\/categories_v2\/travel\/hotel_","suffix":".png"},"primary":true}],"verified":false,"stats":{"checkinsCount":966,"usersCount":256,"tipCount":8},"rating":8.4,"ratingColor":"73CF42","ratingSignals":37,"venueRatingBlacklisted":true,"allowMenuUrlEdit":true,"beenHere":{"count":0,"marked":false,"lastCheckinExpiredAt":0},"photos":{"count":1,"groups":[{"type":"venue","name":"Fotos do lugar","count":1,"items":[{"id":"524f3fbf498e1c86285cf23d","createdAt":1380925375,"prefix":"https:\/\/igx.4sqi.net\/img\/general\/","suffix":"\/27836553_C7hMoAAB7AjnUadSHJRuNhn4oBi1ARMarubhh0nyxsM.jpg","width":720,"height":960,"user":{"id":"27836553","firstName":"Deborah","lastName":"Moro","gender":"female","photo":{"prefix":"https:\/\/igx.4sqi.net\/img\/user\/","suffix":"\/27836553-FLYXTM5QXCSGWCFG.jpg"}},"visibility":"public"}]}]},"hereNow":{"count":0,"summary":"Não há ninguém aqui","groups":[]},"featuredPhotos":{"count":1,"items":[{"id":"524f3fbf498e1c86285cf23d","createdAt":1380925375,"prefix":"https:\/\/igx.4sqi.net\/img\/general\/","suffix":"\/27836553_C7hMoAAB7AjnUadSHJRuNhn4oBi1ARMarubhh0nyxsM.jpg","width":720,"height":960,"user":{"id":"27836553","firstName":"Deborah","lastName":"Moro","gender":"female","photo":{"prefix":"https:\/\/igx.4sqi.net\/img\/user\/","suffix":"\/27836553-FLYXTM5QXCSGWCFG.jpg"}},"visibility":"public"}]}},"tips":[{"id":"4f4f800be4b08cc4b7627b93","createdAt":1330610187,"text":"Excelente lugar, serviço, atendimento, funcionários, enfim vc é muito bem recebido e o lugar é extremamente bem localizado e aconchegante!","type":"user","canonicalUrl":"https:\/\/foursquare.com\/item\/4f4f800be4b08cc4b7627b93","likes":{"count":3,"groups":[],"summary":"3 curtir"},"logView":true,"agreeCount":3,"disagreeCount":0,"todo":{"count":0},"user":{"id":"22556224","firstName":"Pedro","lastName":"Barreto","gender":"male","photo":{"prefix":"https:\/\/igx.4sqi.net\/img\/user\/","suffix":"\/L4ZHZLFSC4AE04CS.jpg"}}}],"referralId":"e-0-4daf9e75432d64ea9437fe50-3"},{"reasons":{"count":0,"items":[{"summary":"Este lugar é popular","type":"general","reasonName":"globalInteractionReason"}]},"venue":{"id":"4cc9580ebcb1b1f711670e8a","name":"Super Pizza Pan","contact":{"phone":"+551132512425","formattedPhone":"+55 11 3251-2425","twitter":"superpizzapan","facebook":"503967059650133","facebookUsername":"SuperPizzaPan","facebookName":"Super Pizza Pan"},"location":{"address":"R. Treze de Maio, 1452","crossStreet":"R. Carlos Sampaio","lat":-23.566088829983276,"lng":-46.64484838383117,"labeledLatLngs":[{"label":"display","lat":-23.566088829983276,"lng":-46.64484838383117}],"distance":168,"postalCode":"01327-002","cc":"BR","city":"São Paulo","state":"SP","country":"Brasil","formattedAddress":["R. Treze de Maio, 1452 (R. Carlos Sampaio)","São Paulo, SP","01327-002","Brasil"]},"categories":[{"id":"4bf58dd8d48988d1ca941735","name":"Pizzaria","pluralName":"Pizzarias","shortName":"Pizza","icon":{"prefix":"https:\/\/ss3.4sqi.net\/img\/categories_v2\/food\/pizza_","suffix":".png"},"primary":true}],"verified":false,"stats":{"checkinsCount":1676,"usersCount":929,"tipCount":67},"url":"http:\/\/www.superpizzapan.com.br","price":{"tier":3,"message":"Caro","currency":"$"},"rating":8.4,"ratingColor":"73CF42","ratingSignals":182,"allowMenuUrlEdit":true,"beenHere":{"count":0,"marked":false,"lastCheckinExpiredAt":0},"hours":{"status":"Fechado até 18:00 amanhã","richStatus":{"entities":[],"text":"Fechado até 18:00 amanhã"},"isOpen":false,"isLocalHoliday":false},"photos":{"count":1,"groups":[{"type":"venue","name":"Fotos do lugar","count":1,"items":[{"id":"51682fe5e4b0e6fe612098cf","createdAt":1365782501,"prefix":"https:\/\/igx.4sqi.net\/img\/general\/","suffix":"\/26105935_1Z8Uq0JHIGyIQtDex3QNlRQzf_qNZ1KIOVPeWw9Btsk.jpg","width":720,"height":538,"user":{"id":"26105935","firstName":"Tatiana","lastName":"Alves","gender":"female","photo":{"prefix":"https:\/\/igx.4sqi.net\/img\/user\/","suffix":"\/2F4QQ0D3454PSH3T.jpg"}},"visibility":"public"}]}]},"hereNow":{"count":0,"summary":"Não há ninguém aqui","groups":[]},"featuredPhotos":{"count":1,"items":[{"id":"51682fe5e4b0e6fe612098cf","createdAt":1365782501,"prefix":"https:\/\/igx.4sqi.net\/img\/general\/","suffix":"\/26105935_1Z8Uq0JHIGyIQtDex3QNlRQzf_qNZ1KIOVPeWw9Btsk.jpg","width":720,"height":538,"user":{"id":"26105935","firstName":"Tatiana","lastName":"Alves","gender":"female","photo":{"prefix":"https:\/\/igx.4sqi.net\/img\/user\/","suffix":"\/2F4QQ0D3454PSH3T.jpg"}},"visibility":"public"}]}},"tips":[{"id":"5232686d11d2bfe19356c5f5","createdAt":1379035245,"text":"Um pessoal muito educado. Pizza de frango philadelphia é só amor.","type":"user","canonicalUrl":"https:\/\/foursquare.com\/item\/5232686d11d2bfe19356c5f5","likes":{"count":8,"groups":[],"summary":"8 curtir"},"logView":true,"agreeCount":8,"disagreeCount":0,"todo":{"count":0},"user":{"id":"13832021","firstName":"Bruno","lastName":"Farias","gender":"male","photo":{"prefix":"https:\/\/igx.4sqi.net\/img\/user\/","suffix":"\/13832021-XTCKDCXOBP2JOQCB.jpg"}}}],"referralId":"e-0-4cc9580ebcb1b1f711670e8a-4"},{"reasons":{"count":0,"items":[{"summary":"Este lugar é popular","type":"general","reasonName":"globalInteractionReason"}]},"venue":{"id":"5497e61a498e8683bf27da46","name":"Starbucks","contact":{"phone":"+551132536092","formattedPhone":"+55 11 3253-6092","twitter":"starbucksbrasil","facebook":"129956967021642","facebookUsername":"StarbucksBrasil","facebookName":"Starbucks Brasil"},"location":{"address":"Av. Paulista, 500","lat":-23.568144081454573,"lng":-46.64826717359801,"labeledLatLngs":[{"label":"display","lat":-23.568144081454573,"lng":-46.64826717359801}],"distance":255,"postalCode":"01310-000","cc":"BR","neighborhood":"Bela Vista","city":"São Paulo","state":"SP","country":"Brasil","formattedAddress":["Av. Paulista, 500","São Paulo, SP","01310-000","Brasil"]},"categories":[{"id":"4bf58dd8d48988d1e0931735","name":"Cafeteria","pluralName":"Cafeterias","shortName":"Cafeteria","icon":{"prefix":"https:\/\/ss3.4sqi.net\/img\/categories_v2\/food\/coffeeshop_","suffix":".png"},"primary":true}],"verified":false,"stats":{"checkinsCount":12008,"usersCount":5726,"tipCount":117},"url":"http:\/\/www.starbucks.com.br","price":{"tier":3,"message":"Caro","currency":"$"},"rating":8.8,"ratingColor":"73CF42","ratingSignals":1313,"menu":{"type":"Menu","label":"Menu","anchor":"Exibir menu","url":"http:\/\/www.starbucks.com.br\/menu-list","mobileUrl":"http:\/\/www.starbucks.com.br\/menu-list","externalUrl":"http:\/\/www.starbucks.com.br\/menu-list"},"allowMenuUrlEdit":true,"beenHere":{"count":0,"marked":false,"lastCheckinExpiredAt":0},"hours":{"status":"Fechado até 6:30 amanhã","richStatus":{"entities":[],"text":"Fechado até 6:30 amanhã"},"isOpen":false,"isLocalHoliday":false},"photos":{"count":1,"groups":[{"type":"venue","name":"Fotos do lugar","count":1,"items":[{"id":"572666c2498e8f4ce4f57ce6","createdAt":1462134466,"prefix":"https:\/\/igx.4sqi.net\/img\/general\/","suffix":"\/18122405_h1HuXwGaUjbNbQ0JH5ppE0xYEChZAUq9Pdv1QHa-Vr8.jpg","width":1920,"height":1440,"user":{"id":"18122405","firstName":"Pollyanna","lastName":"Guimaraes","gender":"female","photo":{"prefix":"https:\/\/igx.4sqi.net\/img\/user\/","suffix":"\/AZA0PNXLHBDL2GWZ.jpg"}},"visibility":"public"}]}]},"hereNow":{"count":0,"summary":"Não há ninguém aqui","groups":[]},"featuredPhotos":{"count":1,"items":[{"id":"572666c2498e8f4ce4f57ce6","createdAt":1462134466,"prefix":"https:\/\/igx.4sqi.net\/img\/general\/","suffix":"\/18122405_h1HuXwGaUjbNbQ0JH5ppE0xYEChZAUq9Pdv1QHa-Vr8.jpg","width":1920,"height":1440,"user":{"id":"18122405","firstName":"Pollyanna","lastName":"Guimaraes","gender":"female","photo":{"prefix":"https:\/\/igx.4sqi.net\/img\/user\/","suffix":"\/AZA0PNXLHBDL2GWZ.jpg"}},"visibility":"public"}]}},"tips":[{"id":"5505cfba498ee9fd0d434c97","createdAt":1426444218,"text":"sei lá, não entendo a dificuldade das pessoas em escolher o pedido enquanto estão na fila. tem que esperar chegar na boca do caixa pra ~começar~ a pensar no que vai pedir. isso explica as filas.","type":"user","canonicalUrl":"https:\/\/foursquare.com\/item\/5505cfba498ee9fd0d434c97","likes":{"count":8,"groups":[],"summary":"8 curtir"},"logView":true,"agreeCount":8,"disagreeCount":0,"todo":{"count":1},"user":{"id":"32422205","firstName":"Giovanna","lastName":"M.","gender":"female","photo":{"prefix":"https:\/\/igx.4sqi.net\/img\/user\/","suffix":"\/IY2YLUVDHF0QFKRC.jpg"}}}],"referralId":"e-0-5497e61a498e8683bf27da46-5"},{"reasons":{"count":0,"items":[{"summary":"Este lugar é popular","type":"general","reasonName":"globalInteractionReason"}]},"venue":{"id":"4d4bf1a5a79a6a31247278a3","name":"Empório Amino Doces","contact":{"phone":"+551131710793","formattedPhone":"+55 11 3171-0793"},"location":{"address":"Av. Brigadeiro Luís Antônio, 2195","crossStreet":"Av. Paulista","lat":-23.5669865624208,"lng":-46.64869274147041,"labeledLatLngs":[{"label":"display","lat":-23.5669865624208,"lng":-46.64869274147041}],"distance":237,"cc":"BR","city":"São Paulo","state":"SP","country":"Brasil","formattedAddress":["Av. Brigadeiro Luís Antônio, 2195 (Av. Paulista)","São Paulo, SP","Brasil"]},"categories":[{"id":"4bf58dd8d48988d117951735","name":"Loja de Doces","pluralName":"Lojas de Doces","shortName":"Loja de Doces","icon":{"prefix":"https:\/\/ss3.4sqi.net\/img\/categories_v2\/shops\/candystore_","suffix":".png"},"primary":true}],"verified":false,"stats":{"checkinsCount":1248,"usersCount":464,"tipCount":37},"rating":8.5,"ratingColor":"73CF42","ratingSignals":118,"allowMenuUrlEdit":true,"beenHere":{"count":0,"marked":false,"lastCheckinExpiredAt":0},"hours":{"isOpen":false,"isLocalHoliday":false},"photos":{"count":1,"groups":[{"type":"venue","name":"Fotos do lugar","count":1,"items":[{"id":"53938dc1498e4ca6f952b4cf","createdAt":1402179009,"prefix":"https:\/\/igx.4sqi.net\/img\/general\/","suffix":"\/22980545_jNCfU5ElVV3W9WkkTko2muEvUyh8j7QrD8CTm2Lf1UQ.jpg","width":960,"height":720,"user":{"id":"22980545","firstName":"Ana","lastName":"d V","gender":"female","photo":{"prefix":"https:\/\/igx.4sqi.net\/img\/user\/","suffix":"\/22980545-2DQU35HQW24OQS4L.jpg"}},"visibility":"public"}]}]},"hereNow":{"count":0,"summary":"Não há ninguém aqui","groups":[]},"featuredPhotos":{"count":1,"items":[{"id":"53938dc1498e4ca6f952b4cf","createdAt":1402179009,"prefix":"https:\/\/igx.4sqi.net\/img\/general\/","suffix":"\/22980545_jNCfU5ElVV3W9WkkTko2muEvUyh8j7QrD8CTm2Lf1UQ.jpg","width":960,"height":720,"user":{"id":"22980545","firstName":"Ana","lastName":"d V","gender":"female","photo":{"prefix":"https:\/\/igx.4sqi.net\/img\/user\/","suffix":"\/22980545-2DQU35HQW24OQS4L.jpg"}},"visibility":"public"}]}},"tips":[{"id":"5465437d498e500758b22e44","createdAt":1415922557,"text":"Fiquei encantada com o empório! Os doces têm preço muito bom e encontrei importados que não encontro em nenhum outro lugar (e com preço justo!). M&M's Pretzel, Chicago Popcorn e caixa de Mac & Cheese","type":"user","canonicalUrl":"https:\/\/foursquare.com\/item\/5465437d498e500758b22e44","likes":{"count":7,"groups":[],"summary":"7 curtir"},"logView":true,"agreeCount":7,"disagreeCount":0,"todo":{"count":4},"user":{"id":"22455593","firstName":"Dani","lastName":"Al","gender":"female","photo":{"prefix":"https:\/\/igx.4sqi.net\/img\/user\/","suffix":"\/22455593_UGO70W0W_rjGgqjuTiVTYC16R9HHGeXEeytcIszGKuQso45LNjy0LE_3Ya64E1ksZsWlLgn8f.jpg"}}}],"referralId":"e-0-4d4bf1a5a79a6a31247278a3-6"},{"reasons":{"count":0,"items":[{"summary":"Este lugar é popular","type":"general","reasonName":"globalInteractionReason"}]},"venue":{"id":"4b9c2700f964a5207c4f36e3","name":"LimeTime Hostels","contact":{"phone":"+551129355463","formattedPhone":"+55 11 2935-5463","twitter":"limetimehostels","facebook":"37743208307","facebookUsername":"limetimehostels","facebookName":"LimeTime Hostels - São Paulo"},"location":{"address":"R. Treze de Maio, 1552","lat":-23.566814159295877,"lng":-46.644654818870116,"labeledLatLngs":[{"label":"display","lat":-23.566814159295877,"lng":-46.644654818870116}],"distance":179,"postalCode":"01327-002","cc":"BR","city":"São Paulo","state":"SP","country":"Brasil","formattedAddress":["R. Treze de Maio, 1552","São Paulo, SP","01327-002","Brasil"]},"categories":[{"id":"4bf58dd8d48988d1ee931735","name":"Albergue","pluralName":"Albergues","shortName":"Albergue","icon":{"prefix":"https:\/\/ss3.4sqi.net\/img\/categories_v2\/travel\/hostel_","suffix":".png"},"primary":true}],"verified":true,"stats":{"checkinsCount":1638,"usersCount":644,"tipCount":23},"url":"http:\/\/www.limetimehostels.com","rating":8.3,"ratingColor":"73CF42","ratingSignals":87,"venueRatingBlacklisted":true,"allowMenuUrlEdit":true,"beenHere":{"count":0,"marked":false,"lastCheckinExpiredAt":0},"hours":{"status":"Provavelmente aberto","richStatus":{"entities":[],"text":"Provavelmente aberto"},"isOpen":true,"isLocalHoliday":false},"photos":{"count":1,"groups":[{"type":"venue","name":"Fotos do lugar","count":1,"items":[{"id":"5114e478e4b0830253000f16","createdAt":1360323704,"prefix":"https:\/\/igx.4sqi.net\/img\/general\/","suffix":"\/417315_gJPXiOqQ2aprbYPrZyAW1-JwqPfxaPs_s0KTREMZywM.jpg","width":612,"height":612,"user":{"id":"417315","firstName":"Rebiscoito","gender":"female","photo":{"prefix":"https:\/\/igx.4sqi.net\/img\/user\/","suffix":"\/WCBHEENOLGXMTMBY.jpg"}},"visibility":"public"}]}]},"storeId":"","hereNow":{"count":0,"summary":"Não há ninguém aqui","groups":[]},"featuredPhotos":{"count":1,"items":[{"id":"5114e478e4b0830253000f16","createdAt":1360323704,"prefix":"https:\/\/igx.4sqi.net\/img\/general\/","suffix":"\/417315_gJPXiOqQ2aprbYPrZyAW1-JwqPfxaPs_s0KTREMZywM.jpg","width":612,"height":612,"user":{"id":"417315","firstName":"Rebiscoito","gender":"female","photo":{"prefix":"https:\/\/igx.4sqi.net\/img\/user\/","suffix":"\/WCBHEENOLGXMTMBY.jpg"}},"visibility":"public"}]}},"tips":[{"id":"4bafb0de70c603bbb90096b4","createdAt":1269805278,"text":"Free caipirinhas for the guests","type":"user","canonicalUrl":"https:\/\/foursquare.com\/item\/4bafb0de70c603bbb90096b4","likes":{"count":13,"groups":[],"summary":"13 curtir"},"logView":true,"agreeCount":3,"disagreeCount":0,"todo":{"count":4},"user":{"id":"720784","firstName":"Alberto","lastName":"Azevedo","gender":"male","photo":{"prefix":"https:\/\/igx.4sqi.net\/img\/user\/","suffix":"\/QGOHP1TTGQHVZO5E.jpg"}}}],"referralId":"e-0-4b9c2700f964a5207c4f36e3-7"},{"reasons":{"count":0,"items":[{"summary":"Este lugar é popular","type":"general","reasonName":"globalInteractionReason"}]},"venue":{"id":"4b48ec41f964a5208a5d26e3","name":"Livraria Martins Fontes","contact":{"phone":"+551121679900","formattedPhone":"+55 11 2167-9900"},"location":{"address":"Av. Paulista, 509","crossStreet":"Av. Brigadeiro Luís Antônio","lat":-23.56823091088395,"lng":-46.64882713071752,"labeledLatLngs":[{"label":"display","lat":-23.56823091088395,"lng":-46.64882713071752}],"distance":306,"postalCode":"01311-910","cc":"BR","neighborhood":"Avenida Paulista","city":"São Paulo","state":"SP","country":"Brasil","formattedAddress":["Av. Paulista, 509 (Av. Brigadeiro Luís Antônio)","São Paulo, SP","01311-910","Brasil"]},"categories":[{"id":"4bf58dd8d48988d114951735","name":"Livraria","pluralName":"Livrarias","shortName":"Livraria","icon":{"prefix":"https:\/\/ss3.4sqi.net\/img\/categories_v2\/shops\/bookstore_","suffix":".png"},"primary":true}],"verified":false,"stats":{"checkinsCount":11698,"usersCount":6134,"tipCount":160},"url":"http:\/\/www.martinsfontespaulista.com.br","price":{"tier":2,"message":"Razoável","currency":"$"},"rating":9.2,"ratingColor":"00B551","ratingSignals":988,"allowMenuUrlEdit":true,"beenHere":{"count":0,"marked":false,"lastCheckinExpiredAt":0},"hours":{"status":"Fechado até 9:00 amanhã","richStatus":{"entities":[],"text":"Fechado até 9:00 amanhã"},"isOpen":false,"isLocalHoliday":false},"photos":{"count":1,"groups":[{"type":"venue","name":"Fotos do lugar","count":1,"items":[{"id":"4e7dc1f4b8f7246c57b3238f","createdAt":1316864500,"prefix":"https:\/\/igx.4sqi.net\/img\/general\/","suffix":"\/EET44GP42DRJK3SSXVYELFID3HVQNQ55IK4T1ABWL0ZPR3S3.jpg","width":537,"height":720,"user":{"id":"6311960","firstName":"Anderson","lastName":"Mattozinhos de Castro","gender":"male","photo":{"prefix":"https:\/\/igx.4sqi.net\/img\/user\/","suffix":"\/DU2Z3CWTIRMJLXXU.jpg"}},"visibility":"public"}]}]},"hereNow":{"count":1,"summary":"Uma outra pessoa está aqui","groups":[{"type":"others","name":"Outras pessoas aqui","count":1,"items":[]}]},"featuredPhotos":{"count":1,"items":[{"id":"4e7dc1f4b8f7246c57b3238f","createdAt":1316864500,"prefix":"https:\/\/igx.4sqi.net\/img\/general\/","suffix":"\/EET44GP42DRJK3SSXVYELFID3HVQNQ55IK4T1ABWL0ZPR3S3.jpg","width":537,"height":720,"user":{"id":"6311960","firstName":"Anderson","lastName":"Mattozinhos de Castro","gender":"male","photo":{"prefix":"https:\/\/igx.4sqi.net\/img\/user\/","suffix":"\/DU2Z3CWTIRMJLXXU.jpg"}},"visibility":"public"}]}},"tips":[{"id":"4d02400c0dae37042dc7c842","createdAt":1291993100,"text":"O local é muito aconchegante e convidativo para ler um livro.","type":"user","canonicalUrl":"https:\/\/foursquare.com\/item\/4d02400c0dae37042dc7c842","likes":{"count":8,"groups":[],"summary":"8 curtir"},"logView":true,"agreeCount":8,"disagreeCount":0,"todo":{"count":0},"user":{"id":"4705320","firstName":"Gabriel","lastName":"Brasil","gender":"male","photo":{"prefix":"https:\/\/igx.4sqi.net\/img\/user\/","suffix":"\/PSPONELQCRHEOHOX.jpg"}}}],"referralId":"e-0-4b48ec41f964a5208a5d26e3-8"},{"reasons":{"count":0,"items":[{"summary":"Este lugar é popular","type":"general","reasonName":"globalInteractionReason"}]},"venue":{"id":"4ba661e8f964a520664c39e3","name":"Aspargus","contact":{},"location":{"address":"Av. Paulista, 352","lat":-23.568511409509448,"lng":-46.6468423938273,"labeledLatLngs":[{"label":"display","lat":-23.568511409509448,"lng":-46.6468423938273}],"distance":215,"cc":"BR","city":"São Paulo","state":"SP","country":"Brasil","formattedAddress":["Av. Paulista, 352","São Paulo, SP","Brasil"]},"categories":[{"id":"4bf58dd8d48988d1d3941735","name":"Restaurante Vegetariano \/ Vegano","pluralName":"Restaurantes Vegetarianos \/ Veganos","shortName":"Vegetariano \/ Vegano","icon":{"prefix":"https:\/\/ss3.4sqi.net\/img\/categories_v2\/food\/vegetarian_","suffix":".png"},"primary":true}],"verified":false,"stats":{"checkinsCount":3563,"usersCount":1318,"tipCount":68},"price":{"tier":2,"message":"Razoável","currency":"$"},"rating":8.2,"ratingColor":"73CF42","ratingSignals":298,"allowMenuUrlEdit":true,"beenHere":{"count":0,"marked":false,"lastCheckinExpiredAt":0},"hours":{"isOpen":false,"isLocalHoliday":false},"photos":{"count":1,"groups":[{"type":"venue","name":"Fotos do lugar","count":1,"items":[{"id":"4f2ab890e4b0e2cf5e736392","createdAt":1328199824,"prefix":"https:\/\/igx.4sqi.net\/img\/general\/","suffix":"\/BoKPkJomqRbfu-hAGNq5gu45XVOzFHTQ7gLY-wWURnY.jpg","width":540,"height":720,"user":{"id":"15984684","firstName":"Tatiana","lastName":"Duarte","gender":"female","photo":{"prefix":"https:\/\/igx.4sqi.net\/img\/user\/","suffix":"\/44UCEQKN0ZTMRLH2.jpg"}},"visibility":"public"}]}]},"hereNow":{"count":0,"summary":"Não há ninguém aqui","groups":[]},"featuredPhotos":{"count":1,"items":[{"id":"4f2ab890e4b0e2cf5e736392","createdAt":1328199824,"prefix":"https:\/\/igx.4sqi.net\/img\/general\/","suffix":"\/BoKPkJomqRbfu-hAGNq5gu45XVOzFHTQ7gLY-wWURnY.jpg","width":540,"height":720,"user":{"id":"15984684","firstName":"Tatiana","lastName":"Duarte","gender":"female","photo":{"prefix":"https:\/\/igx.4sqi.net\/img\/user\/","suffix":"\/44UCEQKN0ZTMRLH2.jpg"}},"visibility":"public"}]}},"tips":[{"id":"50575f2ae4b08e1d3eca4cfc","createdAt":1347903274,"text":"Um excelente restaurante vegetariano mesmo para aqueles que não são. Muita variedade de saladas e pratos quentes. Sobremesa e suco inclusos no valor do buffet, que é fixo. Recomendo.","type":"user","canonicalUrl":"https:\/\/foursquare.com\/item\/50575f2ae4b08e1d3eca4cfc","likes":{"count":13,"groups":[],"summary":"13 curtir"},"logView":true,"agreeCount":13,"disagreeCount":0,"todo":{"count":0},"user":{"id":"35882708","firstName":"Lucio","lastName":"Dorazio","gender":"male","photo":{"prefix":"https:\/\/igx.4sqi.net\/img\/user\/","suffix":"\/35882708-GRHHN3LQPULXWX0Q.jpg"}}}],"referralId":"e-0-4ba661e8f964a520664c39e3-9"}]}]}}